{"type":"Feature","properties":{"id":"5b9483a6a29f639321a2e325","index":13,"guid":"0244648c-096b-43ee-a488-717835e71f80","isAlive":true,"picture":"https://rawhideio.github.io/site/data/photos/7.png","age":27,"eyeColor":"blue","sex":"female","company":"QUILK","phone":"+1 (821) 591-2242","address":"722 Glendale Court, Russellville, Connecticut, 58397","notes":["Lorem cillum aliquip commodo dolor. Ipsum ut mollit cillum nulla exercitation velit laboris qui duis. Incididunt laborum irure sunt exercitation fugiat Lorem. Esse laboris esse aliqua ad enim. In nulla pariatur deserunt veniam laboris adipisicing consequat sint sit tempor ullamco. Enim sit qui reprehenderit labore."],"registered":"Saturday, July 11, 2015 1:27 PM","sire":"5b9483a6852e98553cb33354","dam":"5b9483a6c19671de7309b1cb","epd":{"CED":16,"BW":2,"WW":93,"YW":58,"RADG":1,"DMI":0,"YH":1,"SC":1,"Doc":"-13","HP":7,"CEM":"-7","Milk":14,"MW":"-68","MH":"-1","EN":27,"CW":67,"Marb":2,"RE":1,"Fat":0,"W":"-7","F":124,"G":"-16","QG":33,"YG":"-11","B":104},"genes":["WSN","QAR","KBB","RNK","RRS"]},"geometry":{"type":"Point","coordinates":[-108.6683325194671,44.779083471481464]}}