{"type":"Feature","properties":{"id":"5b9483a6d441aa4a5bf78cd9","index":39,"guid":"7b312190-2c8a-4719-a026-782131ae732a","isAlive":false,"picture":"https://rawhideio.github.io/site/data/photos/2.png","age":23,"eyeColor":"brown","sex":"male","company":"EDECINE","phone":"+1 (897) 551-2850","address":"210 Ditmas Avenue, Mapletown, Tennessee, 13976","notes":["Occaecat labore ad ipsum ad eiusmod ut dolore officia. Duis tempor nisi magna aliqua qui officia sint sit ipsum. Voluptate deserunt in laboris dolore exercitation anim labore est incididunt do est dolore. Elit dolor et incididunt qui commodo voluptate consequat labore reprehenderit pariatur magna velit pariatur. Ea enim veniam cupidatat ipsum labore ullamco ut officia quis. Occaecat dolore anim culpa laboris laborum reprehenderit anim magna sint incididunt eu laborum qui ad."],"registered":"Wednesday, November 12, 2014 3:47 PM","sire":"5b9483a64cfeff0442481db6","dam":"5b9483a6e0d478b4600b0fe8","epd":{"CED":16,"BW":3,"WW":76,"YW":168,"RADG":0,"DMI":1,"YH":"-1","SC":2,"Doc":39,"HP":9,"CEM":8,"Milk":20,"MW":55,"MH":"-2","EN":45,"CW":"-38","Marb":0,"RE":0,"Fat":0,"W":"-11","F":50,"G":63,"QG":17,"YG":14,"B":210},"genes":["KNW","UUL","ZGD","TTB","QAR"]},"geometry":{"type":"Point","coordinates":[-109.08434782132022,42.062973717926674]}}