{"type":"Feature","properties":{"id":"5b9483a613e87b82d81890c9","index":8,"guid":"6b4e3ccf-a36a-4fee-a829-9f387cec9a49","isAlive":false,"picture":"https://rawhideio.github.io/site/data/photos/6.png","age":12,"eyeColor":"green","sex":"male","company":"BYTREX","phone":"+1 (950) 547-2195","address":"371 Campus Place, Roulette, Oklahoma, 40863","notes":["Ut sunt officia culpa nostrud est aliqua. Aute laborum voluptate eiusmod consequat ullamco velit ea sit cupidatat elit cupidatat proident mollit. Fugiat ad culpa enim proident eu anim ut quis minim."],"registered":"Tuesday, December 15, 2015 2:55 AM","sire":"5b9483a6e0721c8ee52fd3be","dam":"5b9483a691008757f42624d1","epd":{"CED":10,"BW":6,"WW":88,"YW":172,"RADG":0,"DMI":2,"YH":0,"SC":1,"Doc":7,"HP":10,"CEM":"-12","Milk":8,"MW":13,"MH":0,"EN":48,"CW":5,"Marb":0,"RE":0,"Fat":0,"W":"-2","F":156,"G":"-7","QG":29,"YG":1,"B":78},"genes":["KBB","WSN","ZGD","IHI","QAR"]},"geometry":{"type":"Point","coordinates":[-106.613494052873,42.76523503689797]}}