{"type":"Feature","properties":{"id":"5b9483a6f58adca571d082d0","index":83,"guid":"eb2ae51c-fe6d-492d-acab-d70d6a862620","isAlive":false,"picture":"https://rawhideio.github.io/site/data/photos/2.png","age":25,"eyeColor":"blue","sex":"female","company":"ACCUPRINT","phone":"+1 (995) 519-3223","address":"169 Granite Street, Defiance, Iowa, 21764","notes":["Lorem nostrud elit velit ut id ea do incididunt excepteur reprehenderit. Consequat aute amet voluptate occaecat dolor ea quis nisi in qui culpa velit excepteur. Ipsum qui est est culpa quis esse nulla deserunt do."],"registered":"Sunday, November 5, 2017 2:54 PM","sire":"5b9483a6b0ad133d118cd469","dam":"5b9483a67058ff2662f9f7d9","epd":{"CED":18,"BW":8,"WW":57,"YW":"-26","RADG":1,"DMI":"-1","YH":0,"SC":2,"Doc":29,"HP":11,"CEM":"-10","Milk":47,"MW":74,"MH":"-1","EN":10,"CW":42,"Marb":0,"RE":2,"Fat":0,"W":108,"F":74,"G":1,"QG":39,"YG":"-13","B":"-34"},"genes":["ZGD","WSN","BFN","GWB","RRS"]},"geometry":{"type":"Point","coordinates":[-110.63304573949394,42.58956898226659]}}